MANIFEST.in
setup.py
proton/__init__.py
proton/license.txt
proton/template.py
proton/utils.py
proton/xmlutils.py
proton.egg-info/PKG-INFO
proton.egg-info/SOURCES.txt
proton.egg-info/dependency_links.txt
proton.egg-info/top_level.txt
test/__init__.py
test/basic-append-result.xhtml
test/basic-append.xhtml
test/basic-id-only.xhtml
test/basic-list.xhtml
test/basic-prepend-result.xhtml
test/basic-props.xhtml
test/basic-with-namespace.xml
test/basic-with-script.xhtml
test/basic.xhtml
test/basic_test.py
test/benchmark.py
test/benchmark.xhtml
test/blogexample-result.xhtml
test/blogexample.xhtml
test/blogexample_test.py
test/head.xhtml
test/head_test.py
test/hiding-include.xhtml
test/hiding.xhtml
test/hiding2.xhtml
test/hiding3.xhtml
test/hiding_test.py
test/i18n.xhtml
test/i18n_test.py
test/include1.xhtml
test/include2.xhtml
test/include_test.py
test/repeat-id-only.xhtml
test/repeat.xhtml
test/repeat2.xhtml
test/repeat3.xhtml
test/repeat_complex.py
test/repeat_complex.xhtml
test/repeat_test.py
test/replace.xhtml
test/replace_test.py
test/twotemplates.xhtml
test/twotemplates.xml
test/twotemplates_test.py