Metadata-Version: 2.1
Name: proton
Version: 0.9.1
Summary: Proton Template Engine
Home-page: https://github.com/jasonrbriggs/proton
Author: Jason R Briggs
Author-email: jasonrbriggs@gmail.com
License: LGPL
Platform: 3.0
Platform: 3.1
Platform: 3.2
Platform: 3.3
